comstrip/.python-version
comstrip/__init__.py
comstrip/comstrip.el
comstrip/comstrip.py
comstrip/util.py
comstrip-0.0.1.dist-info/LICENSE
comstrip-0.0.1.dist-info/WHEEL
comstrip-0.0.1.dist-info/METADATA
comstrip-0.0.1.dist-info/RECORD
