Metadata-Version: 2.1
Name: comstrip
Version: 0.0.1
Summary: Universal Code Comment Stripper and Diff Analysis tools leveraging Emacs Language support
Home-page: https://pypi.org/project/comstrip
License: MIT
Author: Timothy C. Quinn
Requires-Python: >=3.7.9,<4.0.0
Classifier: Development Status :: 4 - Beta
Classifier: Environment :: Console
Classifier: Intended Audience :: Developers
Classifier: License :: OSI Approved :: MIT License
Classifier: Operating System :: MacOS :: MacOS X
Classifier: Operating System :: POSIX :: BSD
Classifier: Operating System :: POSIX :: Linux
Classifier: Operating System :: POSIX :: SunOS/Solaris
Classifier: Programming Language :: Python :: 3
Classifier: Programming Language :: Python :: 3 :: Only
Classifier: Programming Language :: Python :: 3.10
Classifier: Programming Language :: Python :: 3.7
Classifier: Programming Language :: Python :: 3.8
Classifier: Programming Language :: Python :: 3.9
Classifier: Topic :: Software Development
Requires-Dist: python-Levenshtein (>=0.12.2)
Requires-Dist: texttable (>=1.6.3)
Requires-Dist: thefuzz (>=0.19.0)
Requires-Dist: tiotrap (>=0.3)
Project-URL: Repository, https://github.com/JavaScriptDude/comstrip
